QuangDinhdemopackage2/__init__.py
QuangDinhdemopackage2/mylib.py
QuangDinhdemopackage2-0.0.1.dist-info/METADATA
QuangDinhdemopackage2-0.0.1.dist-info/WHEEL
QuangDinhdemopackage2-0.0.1.dist-info/top_level.txt
QuangDinhdemopackage2-0.0.1.dist-info/RECORD
