Metadata-Version: 2.1
Name: QuangDinhdemopackage2
Version: 0.0.1
Summary: Sort description
Home-page: https://github.com/juicyDD
Author: Dinh
Author-email: dinh@example.com
License: UNKNOWN
Platform: UNKNOWN
Classifier: Programming Language :: Python :: 3
Classifier: License :: OSI Approved :: MIT License
Classifier: Operating System :: OS Independent
